piudb/__init__.py
piudb/classes.py
piudb/supported_classes.py
piudb-0.1.7.dist-info/LICENSE
piudb-0.1.7.dist-info/METADATA
piudb-0.1.7.dist-info/WHEEL
piudb-0.1.7.dist-info/top_level.txt
piudb-0.1.7.dist-info/RECORD
