Metadata-Version: 2.1
Name: piudb
Version: 0.1.7
Summary: This is a simple package, which can be used as a substitute of database.
